LICENSE
MANIFEST.in
README.rst
dev-requirements.txt
requirements.txt
setup.cfg
setup.py
test-requirements.txt
docs/Makefile
docs/api.rst
docs/conf.py
docs/examples.rst
docs/history.rst
docs/index.rst
sprockets/__init__.py
sprockets.mixins.postgresql.egg-info/PKG-INFO
sprockets.mixins.postgresql.egg-info/SOURCES.txt
sprockets.mixins.postgresql.egg-info/dependency_links.txt
sprockets.mixins.postgresql.egg-info/namespace_packages.txt
sprockets.mixins.postgresql.egg-info/not-zip-safe
sprockets.mixins.postgresql.egg-info/requires.txt
sprockets.mixins.postgresql.egg-info/top_level.txt
sprockets/mixins/__init__.py
sprockets/mixins/postgresql/__init__.py