Metadata-Version: 1.1
Name: sprockets.mixins.postgresql
Version: 1.0.1
Summary: A sprockets mixin that automatically connects to PostgreSQL
Home-page: https://github.com/sprockets/sprockets.mixins.postgresql.git
Author: AWeber Communications
Author-email: api@aweber.com
License: Copyright (c) 2014 AWeber Communications
